filecache/__init__.py
filecache/_version.py
filecache/file_cache.py
filecache/file_cache_path.py
filecache/file_cache_source.py
filecache/file_cache_types.py
filecache/py.typed
rms_filecache-3.1.0.dist-info/licenses/LICENSE
rms_filecache-3.1.0.dist-info/METADATA
rms_filecache-3.1.0.dist-info/WHEEL
rms_filecache-3.1.0.dist-info/top_level.txt
rms_filecache-3.1.0.dist-info/RECORD
