Metadata-Version: 2.4
Name: rms-filecache
Version: 3.1.0
Summary: File cache for files retrieved from the cloud
Maintainer-email: "Robert S. French" <rfrench@seti.org>
License: Apache-2.0
Project-URL: Homepage, https://github.com/SETI/rms-filecache
Project-URL: Documentation, https://rms-filecache.readthedocs.io/en/latest
Project-URL: Repository, https://github.com/SETI/rms-filecache
Project-URL: Source, https://github.com/SETI/rms-filecache
Project-URL: Issues, https://github.com/SETI/rms-filecache/issues
Keywords: Google Cloud Storage,Google Storage,Amazon Web Services,S3,file cache
Classifier: Development Status :: 5 - Production/Stable
Classifier: Natural Language :: English
Classifier: Topic :: Software Development :: Libraries :: Python Modules
Classifier: Topic :: Utilities
Classifier: License :: OSI Approved :: Apache Software License
Classifier: Programming Language :: Python :: 3.10
Classifier: Programming Language :: Python :: 3.11
Classifier: Programming Language :: Python :: 3.12
Classifier: Programming Language :: Python :: 3.13
Classifier: Operating System :: MacOS :: MacOS X
Classifier: Operating System :: POSIX :: Linux
Classifier: Operating System :: Microsoft :: Windows
Requires-Python: >=3.10
License-File: LICENSE
Requires-Dist: boto3
Requires-Dist: filelock
Requires-Dist: google-cloud-storage
Requires-Dist: requests
Requires-Dist: typing_extensions
Dynamic: license-file
